brainpylib_test-0.1.6.dist-info/LICENSE
brainpylib_test-0.1.6.dist-info/WHEEL
brainpylib_test-0.1.6.dist-info/top_level.txt
brainpylib_test-0.1.6.dist-info/RECORD
brainpylib_test-0.1.6.dist-info/METADATA
brainpylib/cpu_ops.cpython-39-x86_64-linux-gnu.so
brainpylib/__init__.py
brainpylib/sparse_ops.py
brainpylib/jitconn_ops.py
brainpylib/gpu_ops.cpython-39-x86_64-linux-gnu.so
brainpylib/compat.py
brainpylib/op_register.py
brainpylib/event_ops.py
brainpylib/_src/errors.py
brainpylib/_src/check.py
brainpylib/_src/__init__.py
brainpylib/_src/tools.py
brainpylib/_src/register_custom_calls.py
brainpylib/_src/compat/event_sum.py
brainpylib/_src/compat/__init__.py
brainpylib/_src/compat/atomic_sum.py
brainpylib/_src/compat/event_prod.py
brainpylib/_src/compat/atomic_prod.py
brainpylib/_src/compat/tests/test_coo_event_sum_gpu.py
brainpylib/_src/compat/tests/test_atomic_sum_gpu.py
brainpylib/_src/compat/tests/test_csr_event_prod_cpu.py
brainpylib/_src/compat/tests/test_atomic_sum_cpu.py
brainpylib/_src/compat/tests/test_csr_event_sum_gpu.py
brainpylib/_src/compat/tests/test_atomic_prod_gpu.py
brainpylib/_src/compat/tests/test_atomic_prod_cpu.py
brainpylib/_src/compat/tests/test_csr_event_sum_cpu.py
brainpylib/_src/jitconn_ops/matvec.py
brainpylib/_src/jitconn_ops/__init__.py
brainpylib/_src/jitconn_ops/matmat.py
brainpylib/_src/jitconn_ops/event_matvec.py
brainpylib/_src/jitconn_ops/tests/matmat_testcase.py
brainpylib/_src/jitconn_ops/tests/test_matmat_gpu.py
brainpylib/_src/jitconn_ops/tests/test_event_matvec.py
brainpylib/_src/jitconn_ops/tests/test_matvec_gpu.py
brainpylib/_src/jitconn_ops/tests/matvec_jitconn_performance.py
brainpylib/_src/jitconn_ops/tests/test_matmat_cpu.py
brainpylib/_src/jitconn_ops/tests/test_event_matvec_gpu.py
brainpylib/_src/jitconn_ops/tests/test_matvec.py
brainpylib/_src/jitconn_ops/tests/event_matvec_jitconn_performance.py
brainpylib/_src/jitconn_ops/tests/matmat_jitconn_performance.py
brainpylib/_src/event_ops/event_info_collection.py
brainpylib/_src/event_ops/__init__.py
brainpylib/_src/event_ops/event_csr_matvec.py
brainpylib/_src/event_ops/tests/test_event_csr_matvec.py
