Metadata-Version: 2.1
Name: brainpylib-test
Version: 0.1.6
Summary: C++/CUDA Library for BrainPy
Home-page: https://github.com/brainpy/brainpylib
Author: BrainPy team
Author-email: chao.brain@qq.com
License: GPL-3.0 license
Keywords: event-driven computation,sparse computation,brainpy
Classifier: Natural Language :: English
Classifier: Operating System :: OS Independent
Classifier: Programming Language :: Python
Classifier: Programming Language :: Python :: 3
Classifier: Programming Language :: Python :: 3.7
Classifier: Programming Language :: Python :: 3.8
Classifier: Programming Language :: Python :: 3.9
Classifier: Programming Language :: Python :: 3.10
Classifier: Intended Audience :: Science/Research
Classifier: License :: OSI Approved :: Apache Software License
Classifier: Topic :: Scientific/Engineering :: Bio-Informatics
Classifier: Topic :: Scientific/Engineering :: Mathematics
Classifier: Topic :: Scientific/Engineering :: Artificial Intelligence
Classifier: Topic :: Software Development :: Libraries
Requires-Python: >=3.7
License-File: LICENSE
Requires-Dist: jax
Requires-Dist: numba
Requires-Dist: numpy
Provides-Extra: test
Requires-Dist: pytest ; extra == 'test'
